{"uid":"49","workoutId":"78799","entryName":"AllFitFiles/2013-09-06-16-50-22.fit","segments":[{"id":"5fa91181-32bf-466b-a9f1-16831ce5abd3","start_offset":467,"end_offset":490,"duration":23,"avg_power":297,"avg_heart_rate":129,"avg_cadence":87,"avg_speed":9.8,"altimeters":-1000,"segmenttype":"auto","rowstate":"CRE","position":0,"segmentname":""},{"id":"eeff7e7d-11c2-477b-9beb-74b8b82038a7","start_offset":902,"end_offset":931,"duration":29,"avg_power":292,"avg_heart_rate":145,"avg_cadence":95,"avg_speed":9.8,"altimeters":3000,"segmenttype":"auto","rowstate":"CRE","position":1,"segmentname":""},{"id":"80779b1c-817b-4735-939c-6c9d6f63c601","start_offset":946,"end_offset":1003,"duration":57,"avg_power":382,"avg_heart_rate":153,"avg_cadence":92,"avg_speed":9.4,"altimeters":11000,"segmenttype":"auto","rowstate":"CRE","position":2,"segmentname":""},{"id":"017fe7f6-ef37-4e48-963e-40ac0ea7d6d7","start_offset":1090,"end_offset":1903,"duration":813,"avg_power":345,"avg_heart_rate":167,"avg_cadence":76,"avg_speed":7.1,"altimeters":227000,"segmenttype":"auto","rowstate":"CRE","position":3,"segmentname":""},{"id":"ac9e808b-aff5-4ff3-b309-6c9f61952af3","start_offset":2461,"end_offset":2497,"duration":36,"avg_power":288,"avg_heart_rate":152,"avg_cadence":76,"avg_speed":9.4,"altimeters":4000,"segmenttype":"auto","rowstate":"CRE","position":4,"segmentname":""},{"id":"3ed801c4-8d75-4643-a76e-9086d28552ab","start_offset":3500,"end_offset":3539,"duration":39,"avg_power":319,"avg_heart_rate":151,"avg_cadence":72,"avg_speed":8.5,"altimeters":9000,"segmenttype":"auto","rowstate":"CRE","position":5,"segmentname":""},{"id":"0b959fab-1515-467b-bb77-7cef352e0ef6","start_offset":3772,"end_offset":3888,"duration":116,"avg_power":269,"avg_heart_rate":153,"avg_cadence":78,"avg_speed":9.1,"altimeters":17000,"segmenttype":"auto","rowstate":"CRE","position":6,"segmentname":""},{"id":"06b2b4f4-2e1a-421b-a7e9-e9e07787cf76","start_offset":4287,"end_offset":4342,"duration":55,"avg_power":350,"avg_heart_rate":157,"avg_cadence":65,"avg_speed":4.5,"altimeters":19000,"segmenttype":"auto","rowstate":"CRE","position":7,"segmentname":""},{"id":"a372f5fa-7395-4e79-a407-ac04684524c8","start_offset":4568,"end_offset":4776,"duration":208,"avg_power":294,"avg_heart_rate":160,"avg_cadence":63,"avg_speed":4.6,"altimeters":60000,"segmenttype":"auto","rowstate":"CRE","position":8,"segmentname":""},{"id":"17c136b2-3e59-4fdf-a3f4-d38df2854d51","start_offset":4793,"end_offset":5494,"duration":701,"avg_power":303,"avg_heart_rate":170,"avg_cadence":61,"avg_speed":4.4,"altimeters":216000,"segmenttype":"auto","rowstate":"CRE","position":9,"segmentname":""},{"id":"49e61416-f893-42f9-89be-2a0e2c89ba1c","start_offset":992,"end_offset":996,"duration":5,"avg_power":481,"avg_heart_rate":162,"avg_cadence":88,"avg_speed":9.13,"altimeters":2000,"segmenttype":"crit","rowstate":"CRE","position":0,"segmentname":""},{"id":"592cb0b5-a9d9-458f-8e15-1382cf5dd8e7","start_offset":982,"end_offset":996,"duration":15,"avg_power":472,"avg_heart_rate":160,"avg_cadence":88,"avg_speed":8.98,"altimeters":4000,"segmenttype":"crit","rowstate":"CRE","position":1,"segmentname":""},{"id":"a6a5eb5f-3572-4d01-a3d3-9d4584e884ec","start_offset":1839,"end_offset":1898,"duration":60,"avg_power":427,"avg_heart_rate":182,"avg_cadence":78,"avg_speed":7.21,"altimeters":22000,"segmenttype":"crit","rowstate":"CRE","position":2,"segmentname":""},{"id":"000aa874-caa3-4371-b6a4-aff677dd53ec","start_offset":1779,"end_offset":1898,"duration":120,"avg_power":398,"avg_heart_rate":181,"avg_cadence":74,"avg_speed":6.72,"altimeters":41000,"segmenttype":"crit","rowstate":"CRE","position":3,"segmentname":""},{"id":"9dcedfd7-ff6b-4db3-9680-361c062062be","start_offset":1659,"end_offset":1898,"duration":240,"avg_power":387,"avg_heart_rate":179,"avg_cadence":71,"avg_speed":6.33,"altimeters":82000,"segmenttype":"crit","rowstate":"CRE","position":4,"segmentname":""},{"id":"64f405c4-a615-4899-801f-a1332f72d891","start_offset":1419,"end_offset":1898,"duration":480,"avg_power":374,"avg_heart_rate":175,"avg_cadence":71,"avg_speed":6.26,"altimeters":163000,"segmenttype":"crit","rowstate":"CRE","position":5,"segmentname":""},{"id":"ed69a931-9c17-48af-a91d-32ebd2518caa","start_offset":1000,"end_offset":1899,"duration":900,"avg_power":337,"avg_heart_rate":166,"avg_cadence":77,"avg_speed":7.33,"altimeters":236000,"segmenttype":"crit","rowstate":"CRE","position":6,"segmentname":""},{"id":"45699596-5359-4955-8e02-495a09c56e35","start_offset":100,"end_offset":1899,"duration":1800,"avg_power":296,"avg_heart_rate":152,"avg_cadence":80,"avg_speed":8.43,"altimeters":286000,"segmenttype":"crit","rowstate":"CRE","position":7,"segmentname":""}]}