{"uid":"49","workoutId":"79058","entryName":"AllFitFiles/2011-08-28-09-34-24.fit","segments":[{"id":"59cf340a-b09a-4b3c-a5d2-d05ea4e671ed","start_offset":971,"end_offset":1011,"duration":40,"avg_power":426,"avg_heart_rate":151,"avg_cadence":85,"avg_speed":8.8,"altimeters":0,"segmenttype":"auto","rowstate":"CRE","position":0,"segmentname":""},{"id":"8aa885a9-d961-43bf-b12b-439c5a46cd60","start_offset":1364,"end_offset":1926,"duration":562,"avg_power":369,"avg_heart_rate":166,"avg_cadence":75,"avg_speed":6.5,"altimeters":0,"segmenttype":"auto","rowstate":"CRE","position":1,"segmentname":""},{"id":"c2495000-eb63-454e-bece-e819bb1f1e73","start_offset":2577,"end_offset":2625,"duration":48,"avg_power":316,"avg_heart_rate":154,"avg_cadence":78,"avg_speed":9.8,"altimeters":0,"segmenttype":"auto","rowstate":"CRE","position":2,"segmentname":""},{"id":"98e6c584-6654-46a8-a3e3-f78cc8604c67","start_offset":3499,"end_offset":3525,"duration":26,"avg_power":299,"avg_heart_rate":147,"avg_cadence":76,"avg_speed":9.1,"altimeters":0,"segmenttype":"auto","rowstate":"CRE","position":3,"segmentname":""},{"id":"e5bc7256-9938-44da-bbfe-5ba04a6a3dda","start_offset":3633,"end_offset":3686,"duration":53,"avg_power":370,"avg_heart_rate":156,"avg_cadence":71,"avg_speed":8.3,"altimeters":0,"segmenttype":"auto","rowstate":"CRE","position":4,"segmentname":""},{"id":"8a21680b-815f-4fcd-9055-23d42d4b2e44","start_offset":3963,"end_offset":4022,"duration":59,"avg_power":293,"avg_heart_rate":151,"avg_cadence":83,"avg_speed":8.8,"altimeters":0,"segmenttype":"auto","rowstate":"CRE","position":5,"segmentname":""},{"id":"c8d03dec-418c-48e0-97a1-a65f4064bab7","start_offset":4392,"end_offset":4417,"duration":25,"avg_power":309,"avg_heart_rate":147,"avg_cadence":71,"avg_speed":7.2,"altimeters":0,"segmenttype":"auto","rowstate":"CRE","position":6,"segmentname":""},{"id":"9e229fbf-2c19-4f5c-8cb6-509bd36c38f1","start_offset":4466,"end_offset":4565,"duration":99,"avg_power":324,"avg_heart_rate":155,"avg_cadence":67,"avg_speed":5.1,"altimeters":0,"segmenttype":"auto","rowstate":"CRE","position":7,"segmentname":""},{"id":"3f631c44-09b5-4dab-96b3-48deaa54d6a0","start_offset":4676,"end_offset":4911,"duration":235,"avg_power":334,"avg_heart_rate":159,"avg_cadence":67,"avg_speed":5.5,"altimeters":0,"segmenttype":"auto","rowstate":"CRE","position":8,"segmentname":""},{"id":"b6d10025-9df5-4fbf-917e-b6aad5ce5e9a","start_offset":4924,"end_offset":5541,"duration":617,"avg_power":337,"avg_heart_rate":165,"avg_cadence":60,"avg_speed":5.1,"altimeters":0,"segmenttype":"auto","rowstate":"CRE","position":9,"segmentname":""},{"id":"e6dbf0dc-db91-4f65-a850-d43faf89b35b","start_offset":2496,"end_offset":2500,"duration":5,"avg_power":690,"avg_heart_rate":131,"avg_cadence":77,"avg_speed":11.44,"altimeters":0,"segmenttype":"crit","rowstate":"CRE","position":0,"segmentname":""},{"id":"fdf8c439-43f4-4063-ac8a-04ec94467db1","start_offset":2194,"end_offset":2208,"duration":15,"avg_power":504,"avg_heart_rate":144,"avg_cadence":52,"avg_speed":4.16,"altimeters":0,"segmenttype":"crit","rowstate":"CRE","position":1,"segmentname":""},{"id":"bd7134f1-fe80-4884-8a0d-9738dfcbd048","start_offset":1863,"end_offset":1922,"duration":60,"avg_power":430,"avg_heart_rate":176,"avg_cadence":79,"avg_speed":7.25,"altimeters":0,"segmenttype":"crit","rowstate":"CRE","position":2,"segmentname":""},{"id":"eb645d12-bc9c-4b8c-87e2-bf3c944735b1","start_offset":1804,"end_offset":1923,"duration":120,"avg_power":405,"avg_heart_rate":174,"avg_cadence":78,"avg_speed":6.91,"altimeters":0,"segmenttype":"crit","rowstate":"CRE","position":3,"segmentname":""},{"id":"748e54d8-5472-4f8e-99d3-24bf9837fcd5","start_offset":1683,"end_offset":1922,"duration":240,"avg_power":383,"avg_heart_rate":172,"avg_cadence":76,"avg_speed":6.49,"altimeters":0,"segmenttype":"crit","rowstate":"CRE","position":4,"segmentname":""},{"id":"fff8b3f3-34f6-4f7a-8c51-9ab9b73bd0e5","start_offset":1444,"end_offset":1923,"duration":480,"avg_power":374,"avg_heart_rate":169,"avg_cadence":76,"avg_speed":6.38,"altimeters":0,"segmenttype":"crit","rowstate":"CRE","position":5,"segmentname":""},{"id":"23d0d055-701b-459f-bd96-e052d6841d87","start_offset":1024,"end_offset":1923,"duration":900,"avg_power":334,"avg_heart_rate":158,"avg_cadence":77,"avg_speed":7.17,"altimeters":0,"segmenttype":"crit","rowstate":"CRE","position":6,"segmentname":""},{"id":"def2a56d-0b2a-4e5c-8b9a-ecc73f718141","start_offset":3739,"end_offset":5538,"duration":1800,"avg_power":298,"avg_heart_rate":154,"avg_cadence":70,"avg_speed":7.25,"altimeters":0,"segmenttype":"crit","rowstate":"CRE","position":7,"segmentname":""}]}