{"uid":"49","workoutId":"78685","entryName":"AllFitFiles/2015-07-26-08-53-16.fit","segments":[{"id":"28cdd2ce-6a33-4a69-bca4-d171f976156a","start_offset":1943,"end_offset":2103,"duration":160,"avg_power":304,"avg_heart_rate":145,"avg_cadence":83,"avg_speed":5.5,"altimeters":46000,"segmenttype":"auto","rowstate":"CRE","position":0,"segmentname":""},{"id":"bfa98c80-36af-41c7-a208-07ccb2e06232","start_offset":2491,"end_offset":2569,"duration":78,"avg_power":288,"avg_heart_rate":139,"avg_cadence":75,"avg_speed":5.9,"altimeters":20000,"segmenttype":"auto","rowstate":"CRE","position":1,"segmentname":""},{"id":"922a81ee-4c66-467b-935c-f35899e53752","start_offset":3196,"end_offset":3227,"duration":31,"avg_power":316,"avg_heart_rate":133,"avg_cadence":77,"avg_speed":6.3,"altimeters":8000,"segmenttype":"auto","rowstate":"CRE","position":2,"segmentname":""},{"id":"7e676f85-94ed-4a7f-a037-3584da23c019","start_offset":4019,"end_offset":4170,"duration":151,"avg_power":286,"avg_heart_rate":138,"avg_cadence":71,"avg_speed":5.2,"altimeters":41000,"segmenttype":"auto","rowstate":"CRE","position":3,"segmentname":""},{"id":"af020108-3472-4ee6-b102-3863427d3e0c","start_offset":5348,"end_offset":5370,"duration":22,"avg_power":317,"avg_heart_rate":134,"avg_cadence":75,"avg_speed":5.9,"altimeters":4000,"segmenttype":"auto","rowstate":"CRE","position":4,"segmentname":""},{"id":"835a9e33-ce46-463f-96f9-8fe8687bdbed","start_offset":6285,"end_offset":6307,"duration":22,"avg_power":301,"avg_heart_rate":132,"avg_cadence":73,"avg_speed":9.1,"altimeters":3000,"segmenttype":"auto","rowstate":"CRE","position":5,"segmentname":""},{"id":"c44174bb-fb11-4e92-aac3-6c3da5f2cb99","start_offset":6568,"end_offset":6740,"duration":172,"avg_power":302,"avg_heart_rate":136,"avg_cadence":68,"avg_speed":2.4,"altimeters":56000,"segmenttype":"auto","rowstate":"CRE","position":6,"segmentname":""},{"id":"a05320a9-e5f1-4ebd-a2e4-ff2cb793a734","start_offset":8317,"end_offset":8408,"duration":91,"avg_power":332,"avg_heart_rate":141,"avg_cadence":67,"avg_speed":5,"altimeters":32000,"segmenttype":"auto","rowstate":"CRE","position":7,"segmentname":""},{"id":"db310202-984b-47d0-b0a8-ffe7c127d547","start_offset":8661,"end_offset":8665,"duration":5,"avg_power":527,"avg_heart_rate":119,"avg_cadence":122,"avg_speed":21.62,"altimeters":-8000,"segmenttype":"crit","rowstate":"CRE","position":0,"segmentname":""},{"id":"54bc95fe-ec5b-4187-a9a5-180f3a709b2c","start_offset":8960,"end_offset":8974,"duration":15,"avg_power":399,"avg_heart_rate":135,"avg_cadence":72,"avg_speed":9.74,"altimeters":1000,"segmenttype":"crit","rowstate":"CRE","position":1,"segmentname":""},{"id":"77005034-d4b4-4502-b70e-a51d56415286","start_offset":8334,"end_offset":8393,"duration":60,"avg_power":341,"avg_heart_rate":144,"avg_cadence":66,"avg_speed":4.87,"altimeters":21000,"segmenttype":"crit","rowstate":"CRE","position":2,"segmentname":""},{"id":"bea49020-627c-499a-80b3-96b6f305cfd5","start_offset":5606,"end_offset":5725,"duration":120,"avg_power":322,"avg_heart_rate":145,"avg_cadence":67,"avg_speed":3.65,"altimeters":43000,"segmenttype":"crit","rowstate":"CRE","position":3,"segmentname":""},{"id":"9e368c75-de91-49b7-bdd8-f61b3a58037f","start_offset":5488,"end_offset":5727,"duration":240,"avg_power":306,"avg_heart_rate":142,"avg_cadence":71,"avg_speed":3.68,"altimeters":80000,"segmenttype":"crit","rowstate":"CRE","position":4,"segmentname":""},{"id":"e08cb496-c727-4bed-a46e-9518bafd2832","start_offset":5343,"end_offset":5822,"duration":480,"avg_power":296,"avg_heart_rate":140,"avg_cadence":73,"avg_speed":3.89,"altimeters":150000,"segmenttype":"crit","rowstate":"CRE","position":5,"segmentname":""},{"id":"d893363a-22f8-426d-9244-8f2b96add9fe","start_offset":6360,"end_offset":7259,"duration":900,"avg_power":274,"avg_heart_rate":135,"avg_cadence":75,"avg_speed":5.86,"altimeters":180000,"segmenttype":"crit","rowstate":"CRE","position":6,"segmentname":""},{"id":"d01e20ba-5357-4786-951a-182438b161aa","start_offset":6370,"end_offset":8169,"duration":1800,"avg_power":259,"avg_heart_rate":134,"avg_cadence":71,"avg_speed":6.15,"altimeters":238000,"segmenttype":"crit","rowstate":"CRE","position":7,"segmentname":""}]}