{"uid":"49","workoutId":"78640","entryName":"AllFitFiles/2014-11-23-08-47-54.fit","segments":[{"id":"4f546376-7c23-44df-b816-513d34424dea","start_offset":214,"end_offset":277,"duration":63,"avg_power":269,"avg_heart_rate":129,"avg_cadence":79,"avg_speed":3.6,"altimeters":17000,"segmenttype":"auto","rowstate":"CRE","position":0,"segmentname":""},{"id":"7b1adcb2-32d8-48fa-bfce-e6c3d9b53bf0","start_offset":394,"end_offset":415,"duration":21,"avg_power":238,"avg_heart_rate":131,"avg_cadence":76,"avg_speed":6.8,"altimeters":1000,"segmenttype":"auto","rowstate":"CRE","position":1,"segmentname":""},{"id":"49ed26dc-d948-4f7f-8439-0d7f5b9756c3","start_offset":531,"end_offset":607,"duration":76,"avg_power":243,"avg_heart_rate":134,"avg_cadence":81,"avg_speed":8.6,"altimeters":2000,"segmenttype":"auto","rowstate":"CRE","position":2,"segmentname":""},{"id":"7d81296a-13af-49e6-88fb-362ad8163de6","start_offset":864,"end_offset":1089,"duration":225,"avg_power":290,"avg_heart_rate":146,"avg_cadence":68,"avg_speed":2,"altimeters":74000,"segmenttype":"auto","rowstate":"CRE","position":3,"segmentname":""},{"id":"a244872e-fa13-403c-8983-2e21e90c0eb8","start_offset":1185,"end_offset":1259,"duration":74,"avg_power":309,"avg_heart_rate":143,"avg_cadence":73,"avg_speed":1.9,"altimeters":27000,"segmenttype":"auto","rowstate":"CRE","position":4,"segmentname":""},{"id":"345fe9f6-b548-47a5-a7f4-861d4303705b","start_offset":1285,"end_offset":1462,"duration":177,"avg_power":257,"avg_heart_rate":140,"avg_cadence":77,"avg_speed":2.3,"altimeters":46000,"segmenttype":"auto","rowstate":"CRE","position":5,"segmentname":""},{"id":"e38e3ba3-0606-4a80-b44c-5cf797d49f14","start_offset":1666,"end_offset":1721,"duration":55,"avg_power":269,"avg_heart_rate":137,"avg_cadence":89,"avg_speed":7.7,"altimeters":4000,"segmenttype":"auto","rowstate":"CRE","position":6,"segmentname":""},{"id":"548837f3-f7ae-4cc4-8361-4c04c7d7a61c","start_offset":1914,"end_offset":2143,"duration":229,"avg_power":261,"avg_heart_rate":137,"avg_cadence":74,"avg_speed":3.9,"altimeters":65000,"segmenttype":"auto","rowstate":"CRE","position":7,"segmentname":""},{"id":"1fcaaca7-0a3b-4af4-ac05-08a8bae2422b","start_offset":2179,"end_offset":2489,"duration":310,"avg_power":270,"avg_heart_rate":146,"avg_cadence":75,"avg_speed":1.9,"altimeters":93000,"segmenttype":"auto","rowstate":"CRE","position":8,"segmentname":""},{"id":"ef077ccd-3d92-4caa-96d3-1a90ac786c91","start_offset":2510,"end_offset":2612,"duration":102,"avg_power":270,"avg_heart_rate":148,"avg_cadence":78,"avg_speed":1.3,"altimeters":30000,"segmenttype":"auto","rowstate":"CRE","position":9,"segmentname":""},{"id":"eb435565-aeb9-469d-9197-2e851c60ce4e","start_offset":2834,"end_offset":2965,"duration":131,"avg_power":252,"avg_heart_rate":140,"avg_cadence":70,"avg_speed":1.5,"altimeters":34000,"segmenttype":"auto","rowstate":"CRE","position":10,"segmentname":""},{"id":"79ea0552-4cd5-4c4c-bfc2-b796f62ba3e3","start_offset":3020,"end_offset":3472,"duration":452,"avg_power":259,"avg_heart_rate":149,"avg_cadence":76,"avg_speed":1.7,"altimeters":115000,"segmenttype":"auto","rowstate":"CRE","position":11,"segmentname":""},{"id":"314435d2-5bdc-44c2-961e-a01d36a6e1a1","start_offset":3593,"end_offset":3692,"duration":99,"avg_power":244,"avg_heart_rate":143,"avg_cadence":93,"avg_speed":12.4,"altimeters":-38000,"segmenttype":"auto","rowstate":"CRE","position":12,"segmentname":""},{"id":"5f678ba2-f79d-484b-b246-530d4addc98e","start_offset":3916,"end_offset":3943,"duration":27,"avg_power":236,"avg_heart_rate":122,"avg_cadence":78,"avg_speed":6.5,"altimeters":3000,"segmenttype":"auto","rowstate":"CRE","position":13,"segmentname":""},{"id":"b8b77507-a229-419d-b796-a61decdeb107","start_offset":3961,"end_offset":4214,"duration":253,"avg_power":253,"avg_heart_rate":136,"avg_cadence":78,"avg_speed":4.5,"altimeters":53000,"segmenttype":"auto","rowstate":"CRE","position":14,"segmentname":""},{"id":"091eee3d-985c-4acf-b4c1-8747fef547c0","start_offset":4225,"end_offset":4277,"duration":52,"avg_power":254,"avg_heart_rate":136,"avg_cadence":86,"avg_speed":7.4,"altimeters":3000,"segmenttype":"auto","rowstate":"CRE","position":15,"segmentname":""},{"id":"094ba6e1-3700-4fa1-8532-8276143190a8","start_offset":4320,"end_offset":4341,"duration":21,"avg_power":313,"avg_heart_rate":130,"avg_cadence":70,"avg_speed":6,"altimeters":4000,"segmenttype":"auto","rowstate":"CRE","position":16,"segmentname":""},{"id":"3fa28e56-d213-47a3-89aa-f976d2addd36","start_offset":4378,"end_offset":4451,"duration":73,"avg_power":310,"avg_heart_rate":139,"avg_cadence":70,"avg_speed":4.1,"altimeters":21000,"segmenttype":"auto","rowstate":"CRE","position":17,"segmentname":""},{"id":"618bfc3a-f3d5-4f0b-822c-b740547e7746","start_offset":4604,"end_offset":4786,"duration":182,"avg_power":260,"avg_heart_rate":141,"avg_cadence":79,"avg_speed":2.5,"altimeters":48000,"segmenttype":"auto","rowstate":"CRE","position":18,"segmentname":""},{"id":"3a21ee7a-756b-4891-973b-210670b0736c","start_offset":4828,"end_offset":4878,"duration":50,"avg_power":300,"avg_heart_rate":138,"avg_cadence":75,"avg_speed":1.2,"altimeters":16000,"segmenttype":"auto","rowstate":"CRE","position":19,"segmentname":""},{"id":"2e75a654-3c66-4da0-9a71-2cc44d2555b4","start_offset":4948,"end_offset":5008,"duration":60,"avg_power":287,"avg_heart_rate":139,"avg_cadence":73,"avg_speed":1.4,"altimeters":17000,"segmenttype":"auto","rowstate":"CRE","position":20,"segmentname":""},{"id":"994838eb-9148-47f7-99aa-bebf9b1de57f","start_offset":5030,"end_offset":5084,"duration":54,"avg_power":266,"avg_heart_rate":147,"avg_cadence":74,"avg_speed":1.5,"altimeters":13000,"segmenttype":"auto","rowstate":"CRE","position":21,"segmentname":""},{"id":"bd9c9905-6e19-4d1e-87d1-e11a504b5bed","start_offset":5323,"end_offset":5372,"duration":49,"avg_power":290,"avg_heart_rate":139,"avg_cadence":73,"avg_speed":4.1,"altimeters":12000,"segmenttype":"auto","rowstate":"CRE","position":22,"segmentname":""},{"id":"16022362-7dfb-474d-b838-7ad915af7f75","start_offset":5412,"end_offset":5514,"duration":102,"avg_power":285,"avg_heart_rate":137,"avg_cadence":77,"avg_speed":6.1,"altimeters":18000,"segmenttype":"auto","rowstate":"CRE","position":23,"segmentname":""},{"id":"9a20ccd7-b2a6-4570-9d97-50b512d76e2e","start_offset":5614,"end_offset":5646,"duration":32,"avg_power":250,"avg_heart_rate":136,"avg_cadence":86,"avg_speed":8.5,"altimeters":0,"segmenttype":"auto","rowstate":"CRE","position":24,"segmentname":""},{"id":"27b77d94-96b6-4dab-b1be-1d834a9b0b75","start_offset":5786,"end_offset":5894,"duration":108,"avg_power":302,"avg_heart_rate":141,"avg_cadence":72,"avg_speed":3.8,"altimeters":32000,"segmenttype":"auto","rowstate":"CRE","position":25,"segmentname":""},{"id":"65bc6c97-6b25-4c43-9eaf-da7d9e14eb05","start_offset":5970,"end_offset":5993,"duration":23,"avg_power":262,"avg_heart_rate":123,"avg_cadence":55,"avg_speed":2.5,"altimeters":5000,"segmenttype":"auto","rowstate":"CRE","position":26,"segmentname":""},{"id":"82b5c95f-d53a-4234-ba5c-50a824c17ea1","start_offset":6285,"end_offset":6318,"duration":33,"avg_power":246,"avg_heart_rate":119,"avg_cadence":70,"avg_speed":5.6,"altimeters":3000,"segmenttype":"auto","rowstate":"CRE","position":27,"segmentname":""},{"id":"49344caf-60d8-4a66-bc2a-c01700db4710","start_offset":6347,"end_offset":6385,"duration":38,"avg_power":305,"avg_heart_rate":136,"avg_cadence":72,"avg_speed":1.9,"altimeters":12000,"segmenttype":"auto","rowstate":"CRE","position":28,"segmentname":""},{"id":"70c894fd-aee4-4d32-a617-0c7fe4d585b8","start_offset":1080,"end_offset":1084,"duration":5,"avg_power":485,"avg_heart_rate":166,"avg_cadence":79,"avg_speed":0.41,"altimeters":2000,"segmenttype":"crit","rowstate":"CRE","position":0,"segmentname":""},{"id":"66055540-6145-4a32-9aa2-9a9bdcdd6197","start_offset":1070,"end_offset":1084,"duration":15,"avg_power":412,"avg_heart_rate":164,"avg_cadence":77,"avg_speed":1.07,"altimeters":5000,"segmenttype":"crit","rowstate":"CRE","position":1,"segmentname":""},{"id":"167db628-7266-41bc-8852-f89dde7865af","start_offset":1025,"end_offset":1084,"duration":60,"avg_power":332,"avg_heart_rate":159,"avg_cadence":72,"avg_speed":1.33,"altimeters":20000,"segmenttype":"crit","rowstate":"CRE","position":2,"segmentname":""},{"id":"daa1f1f9-5181-45e3-89ed-ff0db2ced3db","start_offset":965,"end_offset":1084,"duration":120,"avg_power":309,"avg_heart_rate":153,"avg_cadence":70,"avg_speed":1.42,"altimeters":39000,"segmenttype":"crit","rowstate":"CRE","position":3,"segmentname":""},{"id":"5d3de702-1920-4922-a35b-d9b472efdfa5","start_offset":845,"end_offset":1084,"duration":240,"avg_power":287,"avg_heart_rate":145,"avg_cadence":71,"avg_speed":2.41,"altimeters":74000,"segmenttype":"crit","rowstate":"CRE","position":4,"segmentname":""},{"id":"403d7513-83ea-4e55-a76e-71ea787c243a","start_offset":2326,"end_offset":2805,"duration":480,"avg_power":263,"avg_heart_rate":151,"avg_cadence":76,"avg_speed":1.56,"altimeters":137000,"segmenttype":"crit","rowstate":"CRE","position":5,"segmentname":""},{"id":"27072c13-eb50-407b-abec-c9fd4245a725","start_offset":1912,"end_offset":2811,"duration":900,"avg_power":258,"avg_heart_rate":146,"avg_cadence":76,"avg_speed":2.29,"altimeters":255000,"segmenttype":"crit","rowstate":"CRE","position":6,"segmentname":""},{"id":"59b16b22-f5fd-4c23-a6d2-8e345c864cdd","start_offset":1911,"end_offset":3710,"duration":1800,"avg_power":244,"avg_heart_rate":145,"avg_cadence":74,"avg_speed":2.96,"altimeters":352000,"segmenttype":"crit","rowstate":"CRE","position":7,"segmentname":""}]}