{"uid":"49","workoutId":"78815","entryName":"AllFitFiles/2014-05-03-08-41-52.fit","segments":[{"id":"08be2478-f37f-444e-88ff-543e74ab7b3a","start_offset":861,"end_offset":884,"duration":23,"avg_power":294,"avg_heart_rate":134,"avg_cadence":74,"avg_speed":6.2,"altimeters":7000,"segmenttype":"auto","rowstate":"CRE","position":0,"segmentname":""},{"id":"a88b11d3-01b9-440e-ae7d-0bb3c7e6953d","start_offset":1022,"end_offset":1060,"duration":38,"avg_power":313,"avg_heart_rate":138,"avg_cadence":65,"avg_speed":5,"altimeters":13000,"segmenttype":"auto","rowstate":"CRE","position":1,"segmentname":""},{"id":"ed1ff614-f46f-4aa4-a942-16ddfea15555","start_offset":1200,"end_offset":1272,"duration":72,"avg_power":345,"avg_heart_rate":141,"avg_cadence":70,"avg_speed":5.2,"altimeters":26000,"segmenttype":"auto","rowstate":"CRE","position":2,"segmentname":""},{"id":"506d68ce-f836-4a53-9aaa-f42e6c16afb8","start_offset":1384,"end_offset":1417,"duration":33,"avg_power":315,"avg_heart_rate":137,"avg_cadence":70,"avg_speed":5.4,"altimeters":11000,"segmenttype":"auto","rowstate":"CRE","position":3,"segmentname":""},{"id":"4e076628-a9ed-47ef-9c2c-da9cac098d25","start_offset":1430,"end_offset":1602,"duration":172,"avg_power":331,"avg_heart_rate":151,"avg_cadence":69,"avg_speed":5.2,"altimeters":58000,"segmenttype":"auto","rowstate":"CRE","position":4,"segmentname":""},{"id":"438254ba-f57d-4db8-851e-f0f2232fb928","start_offset":1696,"end_offset":1735,"duration":39,"avg_power":369,"avg_heart_rate":132,"avg_cadence":80,"avg_speed":6.7,"altimeters":14000,"segmenttype":"auto","rowstate":"CRE","position":5,"segmentname":""},{"id":"a83c6918-7f22-47c3-99ec-70fd62c80836","start_offset":1773,"end_offset":1868,"duration":95,"avg_power":347,"avg_heart_rate":143,"avg_cadence":72,"avg_speed":5.4,"altimeters":34000,"segmenttype":"auto","rowstate":"CRE","position":6,"segmentname":""},{"id":"8b6fd4be-92eb-4b91-a181-d699a43d2a66","start_offset":2102,"end_offset":2173,"duration":71,"avg_power":273,"avg_heart_rate":127,"avg_cadence":76,"avg_speed":6.2,"altimeters":17000,"segmenttype":"auto","rowstate":"CRE","position":7,"segmentname":""},{"id":"3381f894-abcc-40a0-96d2-3526b984be0c","start_offset":2206,"end_offset":2408,"duration":202,"avg_power":285,"avg_heart_rate":140,"avg_cadence":66,"avg_speed":4.7,"altimeters":61000,"segmenttype":"auto","rowstate":"CRE","position":8,"segmentname":""},{"id":"6b8347b9-9241-4450-824b-db56b9977950","start_offset":2871,"end_offset":2891,"duration":20,"avg_power":333,"avg_heart_rate":122,"avg_cadence":59,"avg_speed":5.3,"altimeters":6000,"segmenttype":"auto","rowstate":"CRE","position":9,"segmentname":""},{"id":"d7260838-4032-4bb2-bcec-37d3d44d0ab5","start_offset":2988,"end_offset":3020,"duration":32,"avg_power":321,"avg_heart_rate":138,"avg_cadence":70,"avg_speed":5.9,"altimeters":10000,"segmenttype":"auto","rowstate":"CRE","position":10,"segmentname":""},{"id":"83441f49-4f7f-4d3e-a1d8-1521e5c2c0ae","start_offset":3139,"end_offset":3193,"duration":54,"avg_power":313,"avg_heart_rate":136,"avg_cadence":64,"avg_speed":5.3,"altimeters":16000,"segmenttype":"auto","rowstate":"CRE","position":11,"segmentname":""},{"id":"4bf7cf2e-8fd1-4696-8c7f-c8629032a11b","start_offset":3234,"end_offset":3327,"duration":93,"avg_power":290,"avg_heart_rate":136,"avg_cadence":68,"avg_speed":5.1,"altimeters":27000,"segmenttype":"auto","rowstate":"CRE","position":12,"segmentname":""},{"id":"43687b88-5a84-41d8-8535-24437e9de381","start_offset":4226,"end_offset":4262,"duration":36,"avg_power":358,"avg_heart_rate":136,"avg_cadence":78,"avg_speed":11.5,"altimeters":0,"segmenttype":"auto","rowstate":"CRE","position":13,"segmentname":""},{"id":"e2c78b47-3496-4804-a574-b6977094a069","start_offset":4323,"end_offset":4368,"duration":45,"avg_power":331,"avg_heart_rate":135,"avg_cadence":76,"avg_speed":9.6,"altimeters":8000,"segmenttype":"auto","rowstate":"CRE","position":14,"segmentname":""},{"id":"7736f8e6-cee2-4b64-a206-7c4f8d7d1d21","start_offset":4431,"end_offset":4475,"duration":44,"avg_power":348,"avg_heart_rate":137,"avg_cadence":78,"avg_speed":11.6,"altimeters":5000,"segmenttype":"auto","rowstate":"CRE","position":15,"segmentname":""},{"id":"247f11dc-19d3-400f-aa44-be349ae5243f","start_offset":4703,"end_offset":4874,"duration":171,"avg_power":307,"avg_heart_rate":140,"avg_cadence":72,"avg_speed":3.2,"altimeters":61000,"segmenttype":"auto","rowstate":"CRE","position":16,"segmentname":""},{"id":"c34b0296-1df6-4e2b-9451-e045d2b6b54a","start_offset":4887,"end_offset":5021,"duration":134,"avg_power":309,"avg_heart_rate":144,"avg_cadence":73,"avg_speed":4,"altimeters":46000,"segmenttype":"auto","rowstate":"CRE","position":17,"segmentname":""},{"id":"52dc097f-fd53-4878-9a52-867bad866b6b","start_offset":5058,"end_offset":5341,"duration":283,"avg_power":341,"avg_heart_rate":155,"avg_cadence":83,"avg_speed":6.5,"altimeters":94000,"segmenttype":"auto","rowstate":"CRE","position":18,"segmentname":""},{"id":"5c3d884b-87d0-492d-9a39-d0d41d55cc7c","start_offset":5544,"end_offset":5624,"duration":80,"avg_power":343,"avg_heart_rate":139,"avg_cadence":66,"avg_speed":3,"altimeters":32000,"segmenttype":"auto","rowstate":"CRE","position":19,"segmentname":""},{"id":"7d97d519-26e1-43b6-981d-f61df2ddd240","start_offset":5807,"end_offset":6007,"duration":200,"avg_power":291,"avg_heart_rate":143,"avg_cadence":73,"avg_speed":4.3,"altimeters":65000,"segmenttype":"auto","rowstate":"CRE","position":20,"segmentname":""},{"id":"c7fc7a45-320a-4807-82b7-e3d11b6ae885","start_offset":6067,"end_offset":6278,"duration":211,"avg_power":333,"avg_heart_rate":157,"avg_cadence":78,"avg_speed":5.8,"altimeters":71000,"segmenttype":"auto","rowstate":"CRE","position":21,"segmentname":""},{"id":"82f4524b-2e70-4a71-8bde-a02e5b9d02d2","start_offset":6415,"end_offset":6555,"duration":140,"avg_power":316,"avg_heart_rate":145,"avg_cadence":70,"avg_speed":5.3,"altimeters":46000,"segmenttype":"auto","rowstate":"CRE","position":22,"segmentname":""},{"id":"70d8c663-58cf-4a1a-b002-18e7cd2e4026","start_offset":6575,"end_offset":6613,"duration":38,"avg_power":436,"avg_heart_rate":153,"avg_cadence":88,"avg_speed":7.7,"altimeters":14000,"segmenttype":"auto","rowstate":"CRE","position":23,"segmentname":""},{"id":"f973bc3b-1c5c-4b79-b05f-348f43ab7722","start_offset":6593,"end_offset":6597,"duration":5,"avg_power":598,"avg_heart_rate":153,"avg_cadence":85,"avg_speed":8.43,"altimeters":2000,"segmenttype":"crit","rowstate":"CRE","position":0,"segmentname":""},{"id":"d1149474-19b6-450a-a24f-864ea777929c","start_offset":6592,"end_offset":6606,"duration":15,"avg_power":545,"avg_heart_rate":154,"avg_cadence":91,"avg_speed":8.41,"altimeters":6000,"segmenttype":"crit","rowstate":"CRE","position":1,"segmentname":""},{"id":"765a2b91-92c0-4832-941a-b55b0ddd6775","start_offset":5278,"end_offset":5337,"duration":60,"avg_power":393,"avg_heart_rate":163,"avg_cadence":87,"avg_speed":7.49,"altimeters":22000,"segmenttype":"crit","rowstate":"CRE","position":2,"segmentname":""},{"id":"b6336856-c7cb-494b-beb5-24744a7be0d1","start_offset":5218,"end_offset":5337,"duration":120,"avg_power":369,"avg_heart_rate":161,"avg_cadence":84,"avg_speed":7.12,"altimeters":41000,"segmenttype":"crit","rowstate":"CRE","position":3,"segmentname":""},{"id":"c780c283-5c22-49a9-a10d-b2a4aa18f8c3","start_offset":5098,"end_offset":5337,"duration":240,"avg_power":350,"avg_heart_rate":156,"avg_cadence":83,"avg_speed":6.67,"altimeters":81000,"segmenttype":"crit","rowstate":"CRE","position":4,"segmentname":""},{"id":"dfc8b6fb-e735-432a-818c-2b778565dc01","start_offset":4858,"end_offset":5337,"duration":480,"avg_power":321,"avg_heart_rate":150,"avg_cadence":81,"avg_speed":5.58,"altimeters":155000,"segmenttype":"crit","rowstate":"CRE","position":5,"segmentname":""},{"id":"37c322a7-3206-4ace-8f8a-31a091dac556","start_offset":4438,"end_offset":5337,"duration":900,"avg_power":299,"avg_heart_rate":143,"avg_cadence":80,"avg_speed":7.11,"altimeters":177000,"segmenttype":"crit","rowstate":"CRE","position":6,"segmentname":""},{"id":"838f15e9-49b8-4714-b602-4d775f1b280b","start_offset":4433,"end_offset":6232,"duration":1800,"avg_power":272,"avg_heart_rate":141,"avg_cadence":71,"avg_speed":6.62,"altimeters":227000,"segmenttype":"crit","rowstate":"CRE","position":7,"segmentname":""}]}