{"uid":"49","workoutId":"79048","entryName":"AllFitFiles/2008-06-21-11-17-14.fit","segments":[{"id":"dfc3c53b-49fc-4788-9a33-e34497855ad8","start_offset":2516,"end_offset":2537,"duration":21,"avg_power":278,"avg_heart_rate":117,"avg_cadence":69,"avg_speed":7.3,"altimeters":0,"segmenttype":"auto","rowstate":"CRE","position":0,"segmentname":""},{"id":"8a9f5835-cd48-40f9-862b-cbb19b3616c8","start_offset":3779,"end_offset":3850,"duration":71,"avg_power":245,"avg_heart_rate":126,"avg_cadence":74,"avg_speed":4.3,"altimeters":0,"segmenttype":"auto","rowstate":"CRE","position":1,"segmentname":""},{"id":"f8551b29-915d-499a-8d28-7d571c5ca4c2","start_offset":522,"end_offset":526,"duration":5,"avg_power":432,"avg_heart_rate":105,"avg_cadence":75,"avg_speed":6.44,"altimeters":0,"segmenttype":"crit","rowstate":"CRE","position":0,"segmentname":""},{"id":"58f2abd0-589c-43ca-8515-b94d1d4f4ead","start_offset":1137,"end_offset":1151,"duration":15,"avg_power":304,"avg_heart_rate":107,"avg_cadence":76,"avg_speed":6.95,"altimeters":0,"segmenttype":"crit","rowstate":"CRE","position":1,"segmentname":""},{"id":"feb0d0bd-c2d1-4156-aa68-84515303e632","start_offset":3769,"end_offset":3828,"duration":60,"avg_power":248,"avg_heart_rate":124,"avg_cadence":74,"avg_speed":4.4,"altimeters":0,"segmenttype":"crit","rowstate":"CRE","position":2,"segmentname":""},{"id":"df16e5e3-6501-437f-8528-8db12b23b8c9","start_offset":3768,"end_offset":3887,"duration":120,"avg_power":242,"avg_heart_rate":125,"avg_cadence":75,"avg_speed":4.35,"altimeters":0,"segmenttype":"crit","rowstate":"CRE","position":3,"segmentname":""},{"id":"377116bb-16f8-42ee-a5da-10a17d449951","start_offset":3687,"end_offset":3926,"duration":240,"avg_power":227,"avg_heart_rate":121,"avg_cadence":79,"avg_speed":5.11,"altimeters":0,"segmenttype":"crit","rowstate":"CRE","position":4,"segmentname":""},{"id":"cd3c763c-6240-4d41-8344-2f14b087c2d0","start_offset":3455,"end_offset":3934,"duration":480,"avg_power":210,"avg_heart_rate":118,"avg_cadence":83,"avg_speed":6.91,"altimeters":0,"segmenttype":"crit","rowstate":"CRE","position":5,"segmentname":""},{"id":"37cfa73d-57eb-4d43-99b1-8dd28717e09c","start_offset":3030,"end_offset":3929,"duration":900,"avg_power":205,"avg_heart_rate":117,"avg_cadence":84,"avg_speed":8.02,"altimeters":0,"segmenttype":"crit","rowstate":"CRE","position":6,"segmentname":""},{"id":"fbaccfbd-9211-437b-b650-397becb089bd","start_offset":2134,"end_offset":3933,"duration":1800,"avg_power":197,"avg_heart_rate":115,"avg_cadence":83,"avg_speed":8.4,"altimeters":0,"segmenttype":"crit","rowstate":"CRE","position":7,"segmentname":""}]}