{"uid":"49","workoutId":"79069","entryName":"AllFitFiles/2015-04-11-09-00-34.fit","segments":[{"id":"b2aae962-58e4-4b2e-abcf-ce5926883626","start_offset":210,"end_offset":264,"duration":54,"avg_power":326,"avg_heart_rate":130,"avg_cadence":58,"avg_speed":4,"altimeters":16000,"segmenttype":"auto","rowstate":"CRE","position":0,"segmentname":""},{"id":"54bd9f01-611c-4952-a467-3aeaca9ac48b","start_offset":917,"end_offset":1033,"duration":116,"avg_power":288,"avg_heart_rate":139,"avg_cadence":56,"avg_speed":2.3,"altimeters":37000,"segmenttype":"auto","rowstate":"CRE","position":1,"segmentname":""},{"id":"015e13b6-17ed-4c9d-8267-4600638aee44","start_offset":1096,"end_offset":1169,"duration":73,"avg_power":316,"avg_heart_rate":149,"avg_cadence":69,"avg_speed":1.4,"altimeters":22000,"segmenttype":"auto","rowstate":"CRE","position":2,"segmentname":""},{"id":"ae6705ac-9a26-4579-a4d8-03e671898d97","start_offset":1243,"end_offset":1302,"duration":59,"avg_power":333,"avg_heart_rate":146,"avg_cadence":64,"avg_speed":1.7,"altimeters":21000,"segmenttype":"auto","rowstate":"CRE","position":3,"segmentname":""},{"id":"d0a2bf5e-e2f1-4436-a11f-ac501961f327","start_offset":1327,"end_offset":1471,"duration":144,"avg_power":268,"avg_heart_rate":143,"avg_cadence":70,"avg_speed":2.8,"altimeters":41000,"segmenttype":"auto","rowstate":"CRE","position":4,"segmentname":""},{"id":"b9ee872a-0163-4c6e-b076-d6d873c851c7","start_offset":1900,"end_offset":2026,"duration":126,"avg_power":269,"avg_heart_rate":139,"avg_cadence":66,"avg_speed":3.9,"altimeters":35000,"segmenttype":"auto","rowstate":"CRE","position":5,"segmentname":""},{"id":"2ac673e4-87b8-4648-8328-be1a5e757aac","start_offset":2130,"end_offset":2219,"duration":89,"avg_power":286,"avg_heart_rate":144,"avg_cadence":77.1,"avg_speed":1.7,"altimeters":28000,"segmenttype":"auto","rowstate":"CRE","position":6,"segmentname":""},{"id":"b28b7eb0-14e4-48a2-a4a8-42b9ddc66986","start_offset":2372,"end_offset":2444,"duration":72,"avg_power":293,"avg_heart_rate":152,"avg_cadence":84,"avg_speed":1.8,"altimeters":22000,"segmenttype":"auto","rowstate":"CRE","position":7,"segmentname":""},{"id":"087d2005-5842-42c3-9371-648179ccc2db","start_offset":3115,"end_offset":3283,"duration":168,"avg_power":308,"avg_heart_rate":167,"avg_cadence":83,"avg_speed":2.8,"altimeters":51000,"segmenttype":"auto","rowstate":"CRE","position":8,"segmentname":""},{"id":"d9e0a503-b151-447c-bf45-0fbf7a2f7c95","start_offset":3708,"end_offset":3809,"duration":101,"avg_power":270,"avg_heart_rate":141,"avg_cadence":75,"avg_speed":3.9,"altimeters":28000,"segmenttype":"auto","rowstate":"CRE","position":9,"segmentname":""},{"id":"751d9593-9fba-4ad1-a0b0-11cb7feec2b2","start_offset":3838,"end_offset":3867,"duration":29,"avg_power":272,"avg_heart_rate":143,"avg_cadence":69,"avg_speed":4.2,"altimeters":7000,"segmenttype":"auto","rowstate":"CRE","position":10,"segmentname":""},{"id":"2bc5b542-61c1-43c2-8cc0-1daeeef4cacd","start_offset":4141,"end_offset":4212,"duration":71,"avg_power":311,"avg_heart_rate":142,"avg_cadence":80,"avg_speed":4.4,"altimeters":20000,"segmenttype":"auto","rowstate":"CRE","position":11,"segmentname":""},{"id":"d7dad2d2-04b1-494d-b252-fec34caeb5a0","start_offset":1151,"end_offset":1155,"duration":5,"avg_power":455,"avg_heart_rate":158,"avg_cadence":74,"avg_speed":1.33,"altimeters":2000,"segmenttype":"crit","rowstate":"CRE","position":0,"segmentname":""},{"id":"d29fcbcc-b6c0-4da7-ac0d-62188f0db48c","start_offset":1141,"end_offset":1155,"duration":15,"avg_power":381,"avg_heart_rate":155,"avg_cadence":68,"avg_speed":1.22,"altimeters":6000,"segmenttype":"crit","rowstate":"CRE","position":1,"segmentname":""},{"id":"57384688-d9ef-4d78-a321-cacc3616abad","start_offset":3217,"end_offset":3276,"duration":60,"avg_power":335,"avg_heart_rate":170,"avg_cadence":86,"avg_speed":2.81,"altimeters":19000,"segmenttype":"crit","rowstate":"CRE","position":2,"segmentname":""},{"id":"6115610c-654d-49ef-b263-661434dd7bdc","start_offset":3161,"end_offset":3280,"duration":120,"avg_power":320,"avg_heart_rate":167,"avg_cadence":84,"avg_speed":2.68,"altimeters":38000,"segmenttype":"crit","rowstate":"CRE","position":3,"segmentname":""},{"id":"eb093eb3-d0be-4268-b93c-f7734494868a","start_offset":3040,"end_offset":3279,"duration":240,"avg_power":299,"avg_heart_rate":167,"avg_cadence":85,"avg_speed":2.69,"altimeters":71000,"segmenttype":"crit","rowstate":"CRE","position":4,"segmentname":""},{"id":"d2135d6d-3789-446d-a293-bfc211b266d2","start_offset":2800,"end_offset":3279,"duration":480,"avg_power":292,"avg_heart_rate":166,"avg_cadence":83,"avg_speed":2.13,"altimeters":144000,"segmenttype":"crit","rowstate":"CRE","position":5,"segmentname":""},{"id":"1997db65-0c4d-4d1a-9e33-8065c3fc9913","start_offset":2380,"end_offset":3279,"duration":900,"avg_power":285,"avg_heart_rate":163,"avg_cadence":82,"avg_speed":1.86,"altimeters":269000,"segmenttype":"crit","rowstate":"CRE","position":6,"segmentname":""},{"id":"a91fe558-bd0e-414c-a3ce-4db1108a3365","start_offset":1883,"end_offset":3682,"duration":1800,"avg_power":248,"avg_heart_rate":150,"avg_cadence":77,"avg_speed":3.89,"altimeters":297000,"segmenttype":"crit","rowstate":"CRE","position":7,"segmentname":""}]}